map_tiles_downloader/__init__.py
map_tiles_downloader/__main__.py
map_tiles_downloader/cli.py
map_tiles_downloader/downloader.py
map_tiles_downloader/kml_regions.py
map_tiles_downloader/providers.py
map_tiles_downloader/regions.py
map_tiles_downloader/tiling.py
map_tiles_downloader/tui.py
mt_downloader-1.3.3.dist-info/licenses/LICENSE
mt_downloader-1.3.3.dist-info/METADATA
mt_downloader-1.3.3.dist-info/WHEEL
mt_downloader-1.3.3.dist-info/entry_points.txt
mt_downloader-1.3.3.dist-info/top_level.txt
mt_downloader-1.3.3.dist-info/RECORD
