Metadata-Version: 2.4
Name: mt-downloader
Version: 1.3.3
Summary: Fast interactive Meshtastic and MeshCore maps downloader
Author: Peter Javorsky, @tekk
License-Expression: CC-BY-4.0
Project-URL: Homepage, https://github.com/tekk/map-tiles-downloader
Project-URL: Repository, https://github.com/tekk/map-tiles-downloader.git
Keywords: maps,tiles,meshtastic,meshcore,downloader
Classifier: Programming Language :: Python :: 3
Classifier: Operating System :: OS Independent
Classifier: Topic :: Utilities
Requires-Python: >=3.9
License-File: LICENSE
Requires-Dist: aiohttp>=3.9
Requires-Dist: tqdm>=4.65
Requires-Dist: fastkml>=0.12
Requires-Dist: aiofiles>=23.1
Requires-Dist: questionary>=2.0
Requires-Dist: lxml>=5.0
Requires-Dist: geonamescache>=2.0
Dynamic: license-file
